jageocoder/__init__.py
jageocoder/__main__.py
jageocoder/address.py
jageocoder/aza_master.py
jageocoder/dataset.py
jageocoder/dbm/__init__.py
jageocoder/dbm/abstract_table.py
jageocoder/dbm/base_index.py
jageocoder/dbm/base_table.py
jageocoder/dbm/exceptions.py
jageocoder/dbm/types.py
jageocoder/exceptions.py
jageocoder/itaiji.py
jageocoder/itaiji_dic.json
jageocoder/local.py
jageocoder/module.py
jageocoder/node.py
jageocoder/remote.py
jageocoder/result.py
jageocoder/rtree.py
jageocoder/strlib.py
jageocoder/tree.py
jageocoder/trie.py
jageocoder-2.2.0.dist-info/LICENSE
jageocoder-2.2.0.dist-info/METADATA
jageocoder-2.2.0.dist-info/WHEEL
jageocoder-2.2.0.dist-info/entry_points.txt
jageocoder-2.2.0.dist-info/RECORD
