Metadata-Version: 2.3
Name: jageocoder
Version: 2.2.0
Summary: A Japanese-address geocoder for Python.
License: MIT
Keywords: geocoder,Japanese address
Author: Takeshi Sagara
Author-email: sagara@info-proto.com
Requires-Python: >3.9.1
Classifier: Operating System :: MacOS
Classifier: Operating System :: Microsoft :: Windows :: Windows 11
Classifier: Operating System :: POSIX :: Linux
Classifier: License :: OSI Approved :: MIT License
Classifier: Programming Language :: Python :: 3
Provides-Extra: dev
Provides-Extra: doc
Provides-Extra: test
Requires-Dist: deprecated (>=1.2.13)
Requires-Dist: docopt-ng
Requires-Dist: geographiclib (>=2.0)
Requires-Dist: jaconv (>=0.3.9)
Requires-Dist: marisa-trie (>=1.3.1)
Requires-Dist: pytest (>=8.4.1) ; extra == "test"
Requires-Dist: requests
Requires-Dist: rtree (>=1.0.0)
Requires-Dist: sphinx-rtd-theme (>=1.2.0) ; extra == "doc"
Requires-Dist: tqdm (>=4.0.0)
Requires-Dist: twine (>=5.1.1) ; extra == "dev"
Project-URL: Documentation, https://jageocoder.readthedocs.io/ja/latest/
Project-URL: Homepage, https://t-sagara.github.io/jageocoder/
Project-URL: Repository, https://github.com/t-sagara/jageocoder
